auto_sync/__init__.py
auto_sync/_version.py
auto_sync/app.py
auto_sync/config.py
auto_sync/sync.py
auto_sync/util.py
auto_sync/worker.py
auto_sync/resources/__init__.py
auto_sync/resources/auto_sync.ini
auto_sync/resources/example_script.yml
auto_sync/resources/icon.ico
auto_sync/resources/logging.yml
auto_ust/__init__.py
auto_ust/_version.py
auto_ust/app.py
auto_ust/config.py
auto_ust/sync.py
auto_ust/util.py
auto_ust/worker.py
auto_ust/resources/__init__.py
auto_ust/resources/auto_sync.ini
auto_ust/resources/example_script.yml
auto_ust/resources/icon.ico
auto_ust/resources/logging.yml
test_files/__init__.py
auto_ust-1.0.1.dist-info/LICENSE.txt
auto_ust-1.0.1.dist-info/METADATA
auto_ust-1.0.1.dist-info/WHEEL
auto_ust-1.0.1.dist-info/entry_points.txt
auto_ust-1.0.1.dist-info/top_level.txt
auto_ust-1.0.1.dist-info/RECORD
