Metadata-Version: 2.1
Name: auto-ust
Version: 1.0.1
Summary: Sync Tool Automator
Home-page: https://github.com/vossen-adobe/auto-ust
Maintainer: Danimae Vossen
Maintainer-email: vossen.dm@gmail.com
License: MIT
Platform: UNKNOWN
Requires-Dist: click
Requires-Dist: click-default-group
Requires-Dist: pyyaml
Provides-Extra: setup
Requires-Dist: pyinstaller ; extra == 'setup'
Requires-Dist: wheel ; extra == 'setup'
Requires-Dist: twine ; extra == 'setup'
